mftoolbox/__version__.py
mftoolbox/build.py
mftoolbox/constants.py
mftoolbox/cotacoes.py
mftoolbox/cotacoes2.py
mftoolbox/encoding.py
mftoolbox/funcs.py
mftoolbox/init_selenium.py
mftoolbox/key.py
mftoolbox/proventos.py
mftoolbox/raiseerror.py
mftoolbox/timestamp.py
mftoolbox-5.0.5.dist-info/LICENSE
mftoolbox-5.0.5.dist-info/METADATA
mftoolbox-5.0.5.dist-info/WHEEL
mftoolbox-5.0.5.dist-info/top_level.txt
mftoolbox-5.0.5.dist-info/RECORD
