Metadata-Version: 2.1
Name: mftoolbox
Version: 5.0.5
Summary: A set of tools to support my MF2 and MagicFII projects
Home-page: https://github.com/coliveira2001/mftoolbox
Author: Celso Oliveira
Author-email: c.oliveira@live.com
License: UNKNOWN
Platform: UNKNOWN
Classifier: Programming Language :: Python :: 3
Classifier: License :: OSI Approved :: GNU General Public License v3 (GPLv3)
Classifier: Operating System :: OS Independent
Requires-Python: >=3.5
Requires-Dist: configparser
Requires-Dist: zeep
Requires-Dist: lxml
Requires-Dist: bs4
Requires-Dist: selenium
Requires-Dist: progressbar
Requires-Dist: tqdm
